externc/__init__.py
externc/compilers.py
externc-1.1.1.dist-info/LICENSE
externc-1.1.1.dist-info/METADATA
externc-1.1.1.dist-info/WHEEL
externc-1.1.1.dist-info/top_level.txt
externc-1.1.1.dist-info/RECORD
