Metadata-Version: 2.1
Name: externc
Version: 1.1.1
Summary: Inline C function declarations
Author: Fabizocker456
Classifier: License :: OSI Approved :: GNU General Public License v3 (GPLv3)
Classifier: Programming Language :: Python
Classifier: Programming Language :: Python :: 3
Classifier: Operating System :: POSIX :: Linux
Classifier: Programming Language :: C
License-File: LICENSE
